momentest/__init__.py
momentest/common.py
momentest/datasets.py
momentest/dgp.py
momentest/estimation.py
momentest/gmm.py
momentest/inference.py
momentest/output.py
momentest/py.typed
momentest/smm.py
momentest/data/Econ381totpts.txt
momentest-0.1.0.dist-info/licenses/LICENSE
momentest-0.1.0.dist-info/METADATA
momentest-0.1.0.dist-info/WHEEL
momentest-0.1.0.dist-info/top_level.txt
momentest-0.1.0.dist-info/RECORD
