Metadata-Version: 2.4
Name: momentest
Version: 0.1.0
Summary: Simulated Method of Moments (SMM) and Generalized Method of Moments (GMM) estimation in Python
Home-page: https://github.com/haytug/momentest
Author: Harry Aytug
Author-email: Harry Aytug <haytug@gmail.com>
Maintainer-email: Harry Aytug <haytug@gmail.com>
License-Expression: MIT
Project-URL: Homepage, https://github.com/haytug/momentest
Project-URL: Documentation, https://github.com/haytug/momentest#readme
Project-URL: Repository, https://github.com/haytug/momentest
Project-URL: Changelog, https://github.com/haytug/momentest/blob/main/CHANGELOG.md
Project-URL: Issues, https://github.com/haytug/momentest/issues
Keywords: econometrics,SMM,GMM,estimation,simulation,moments,structural estimation,method of moments
Classifier: Development Status :: 4 - Beta
Classifier: Intended Audience :: Science/Research
Classifier: Intended Audience :: Education
Classifier: Operating System :: OS Independent
Classifier: Programming Language :: Python :: 3
Classifier: Programming Language :: Python :: 3.9
Classifier: Programming Language :: Python :: 3.10
Classifier: Programming Language :: Python :: 3.11
Classifier: Programming Language :: Python :: 3.12
Classifier: Topic :: Scientific/Engineering :: Mathematics
Classifier: Topic :: Scientific/Engineering
Classifier: Typing :: Typed
Requires-Python: >=3.9
License-File: LICENSE
Requires-Dist: numpy>=1.20
Requires-Dist: scipy>=1.7
Requires-Dist: joblib>=1.0
Provides-Extra: dev
Requires-Dist: pytest>=7.0; extra == "dev"
Requires-Dist: hypothesis>=6.0; extra == "dev"
Requires-Dist: matplotlib>=3.5; extra == "dev"
Requires-Dist: ruff>=0.1.0; extra == "dev"
Requires-Dist: nbval>=0.10; extra == "dev"
Requires-Dist: jupyter; extra == "dev"
Provides-Extra: plot
Requires-Dist: matplotlib>=3.5; extra == "plot"
Provides-Extra: all
Requires-Dist: matplotlib>=3.5; extra == "all"
Dynamic: license-file
Dynamic: requires-python
